{
  "kind": "collectionType",
  "collectionName": "movies",
  "info": {
    "singularName": "movie",
    "pluralName": "movies",
    "displayName": "Movie"
  },
  "options": {
    "draftAndPublish": true
  },
  "pluginOptions": {},
  "attributes": {
    "title": {
      "type": "string",
      "required": true
    },
    "original_title": {
      "type": "string"
    },
    "original_language": {
      "type": "string"
    },
    "poster_path": {
      "type": "string"
    },
    "backdrop_path": {
      "type": "string"
    },
    "overview": {
      "type": "string"
    },
    "vote_average": {
      "type": "decimal"
    },
    "vote_count": {
      "type": "integer"
    },
    "popularity": {
      "type": "decimal"
    },
    "release_date": {
      "type": "date"
    },
    "adult": {
      "type": "boolean"
    },
    "featured": {
      "type": "boolean",
      "default": false
    },
    "video": {
      "type": "boolean"
    },
    "genre_ids": {
      "type": "json"
    }
  }
}
